{
  "voteRecordsCreatedAt":"2023-07-25T09:05:15.779Z",
  "records": [
    {
      "tokenOwner":"",
      "amount": "9161812211445",
      "validatorVoteAccount": "CXdiCafVFwtTyr4AcAjHtMaow98zqXKq6TRq8GNN9Q15"
    },
    {
      "tokenOwner":"",
      "amount": "0",
      "validatorVoteAccount": "8Rs4wJJVFaRmARmwSvsVSAcSsUb9ZJD4USejuHm974hH"
    },
    {
      "tokenOwner":"",
      "amount": "84144217317746",
      "validatorVoteAccount": "AKoVXpZmi8wSz3sGvCYEygbpdHvSRysWsh36b97iPvKh"
    },
    {
      "tokenOwner":"",
      "amount": "7000000000000",
      "validatorVoteAccount": "DimavhUqvCpWjUZqSFZGLqBiUVUYQ5jZEaCHutKKVs45"
    },
    {
      "tokenOwner":"",
      "amount": "1843126632452",
      "validatorVoteAccount": "78TqFdfHpVULu9EbsouUEGibUJb27DwNLYGsR9qqJJeb"
    },
    {
      "tokenOwner":"",
      "amount": "1562840049455193",
      "validatorVoteAccount": "BeachiopjxQxL7CaHNSZsynApiZCKx9QFVtcWNz3jDBo"
    },
    {
      "tokenOwner":"",
      "amount": "1020000000000",
      "validatorVoteAccount": "4qvFxnUXYjBdcviCwVV7gKcGJMCENEBfS82hSLJUhyvu"
    },
    {
      "tokenOwner":"",
      "amount": "0",
      "validatorVoteAccount": "3CnKZPQn92W8WXG7KTVaFQRk8LJJ3KZbrVVF4ngUxqkg"
    },
    {
      "tokenOwner":"",
      "amount": "6000000000000",
      "validatorVoteAccount": "76DafWkJ6pGK2hoD41HjrM4xTBhfKqrDYDazv13n5ir1"
    },
    {
      "tokenOwner":"",
      "amount": "10552373200897",
      "validatorVoteAccount": "5iJDEVRi1nMLwKAWhYbEokZnvBAe15rgFaHGkggVEP9z"
    },
    {
      "tokenOwner":"",
      "amount": "1539778316551064",
      "validatorVoteAccount": "1234LB7uvDC23rdCQoK8C3jNwnovUNyeKxz8wC3dghJ5"
    },
    {
      "tokenOwner":"",
      "amount": "4054889981963",
      "validatorVoteAccount": "DDCWKg1piRArvzrfu3QC9bPKANz71LpYRuQaSJ2FnNQy"
    },
    {
      "tokenOwner":"",
      "amount": "0",
      "validatorVoteAccount": "2cbRaWTzuPM2zbCaZDNbwft9omJBAyxcavJ6Xp2vQNNk"
    },
    {
      "tokenOwner":"",
      "amount": "2256295838101",
      "validatorVoteAccount": "DeGodsKvJrNTkxcnXVzo4FxpVagQ8XsLKibqxNqJPx27"
    },
    {
      "tokenOwner":"",
      "amount": "0",
      "validatorVoteAccount": "o27rnqfNHPwHsRp2xPXXwWzn2q2dGxn6UD4Rt5KMU5h"
    },
    {
      "tokenOwner":"",
      "amount": "22803591925731",
      "validatorVoteAccount": "GE6atKoWiQ2pt3zL7N13pjNHjdLVys8LinG8qeJLcAiL"
    },
    {
      "tokenOwner":"",
      "amount": "6000000000000",
      "validatorVoteAccount": "DMSuZcavta8L1w1tSiH8bALWjz6Q6KSryGG6m6Az4Qt5"
    },
    {
      "tokenOwner":"",
      "amount": "150000000000000",
      "validatorVoteAccount": "4PsiLMyoUQ7QRn1FFiFCvej4hsUTFzfvJnyN4bj1tmSN"
    },
    {
      "tokenOwner":"",
      "amount": "10386000000000",
      "validatorVoteAccount": "GA2t11gJcmuZ4y7pShTzgYDkxVaJaVQJqkVUqojhPPsT"
    },
    {
      "tokenOwner":"",
      "amount": "6500000000000",
      "validatorVoteAccount": "G8GqFzoEZrxHqV279nYxD5PX1vWWHvxWHkBDkXU2qMy6"
    },
    {
      "tokenOwner":"",
      "amount": "3686253264905",
      "validatorVoteAccount": "99pDvgeCTExgyafsUZB3hwTMcNSqyHaXpEUwWj8U6FUy"
    },
    {
      "tokenOwner":"",
      "amount": "3000000000000",
      "validatorVoteAccount": "Ev3gPXRo6TJeQ2QhxfqWFoasdoGbmDytYvJbUabEHfLf"
    },
    {
      "tokenOwner":"",
      "amount": "7163414525398",
      "validatorVoteAccount": "popBKwvD4E2muAkrW6xpcqrAjahaDG2s69BaknDqTBC"
    },
    {
      "tokenOwner":"",
      "amount": "1000000000000",
      "validatorVoteAccount": "4hoZBjJrFqJf9Bhop5sAwdidFM8qM88EQJQwbfgs1pkP"
    },
    {
      "tokenOwner":"",
      "amount": "741077625000000",
      "validatorVoteAccount": "Luck3DN3HhkV6oc7rPQ1hYGgU3b5AhdKW9o1ob6AyU9"
    },
    {
      "tokenOwner":"",
      "amount": "44278623920273",
      "validatorVoteAccount": "J1to3PQfXidUUhprQWgdKkQAMWPJAEqSJ7amkBDE9qhF"
    },
    {
      "tokenOwner":"",
      "amount": "2704427055171",
      "validatorVoteAccount": "5yHqB3NxovCEMUniQCboaPRMyyQ7kQQF4QqvC4vaz78z"
    },
    {
      "tokenOwner":"",
      "amount": "730135625000000",
      "validatorVoteAccount": "AuBB9st3RqhHBkzZgBSm6SVnHZNJQSHeBWCSkik4bzdA"
    },
      {
      "tokenOwner":"",
      "amount": "1000000000000",
      "validatorVoteAccount": "AfrkokqBnJSSdK4Eo7AX9iFqhbjY4drAMFf6W814tDei"
    },
      {
      "tokenOwner":"",
      "amount": "17986000000000",
      "validatorVoteAccount": "CwSZ17woioM2bqEbaswZJYvx5pemN6t3shBcU6zqPHyG"
    },
      {
      "tokenOwner":"",
      "amount": "2953731026224513",
      "validatorVoteAccount": "DfpdmTsSCBPxCDwZwgBMfjjV8mF8xHkGRcXP8dJBVmrq"
    },
      {
      "tokenOwner":"",
      "amount": "1540841017618012",
      "validatorVoteAccount": "mintrNtxN3PhAB45Pt41XqyKghTTpqcoBkQTZqh96iR"
    },
    {
      "tokenOwner":"",
      "amount": "141354379652505",
      "validatorVoteAccount": "6WL8sgtssHtvrV4enkyXge7w2u7P5NAGHHKRvtgd7cjJ"
    },
      {
      "tokenOwner":"",
      "amount": "1000000000000",
      "validatorVoteAccount": "6n8taYki7RscA1XW7xGmevLcqj855oSgDgjPe1dZyHfW"
    },
      {
      "tokenOwner":"",
      "amount": "3041303222315",
      "validatorVoteAccount": "26WLNWKrYSyPkQF2NU9LgLSRXGiXWjhPnvspG8ibFh63"
    },
      {
      "tokenOwner":"",
      "amount": "3994797725161",
      "validatorVoteAccount": "GAnbgkZq584QAdfZZzX8aCiKvDYcqszY3jGCiwqm3a9h"
    },
      {
      "tokenOwner":"",
      "amount": "6586084972944",
      "validatorVoteAccount": "5nH6sYJNSa71DCBQHgRCsX1dh5W1bWrUPeYieo9xyZ7f"
    },
    {
      "tokenOwner":"",
      "amount": "3093509335489321",
      "validatorVoteAccount": "7K8DVxtNJGnMtUY1CQJT5jcs8sFGSZTDiG7kowvFpECh"
    },
      {
      "tokenOwner":"",
      "amount": "503750000000",
      "validatorVoteAccount": "CZw1sSfjZbCccsk2kTjbFeVSgfzEgV1JxHEsEW69Qce9"
    },
    {
      "tokenOwner":"",
      "amount": "120451664145430",
      "validatorVoteAccount": "gangtRyGPTvYWb8K3xS2feJQaCks4iJ7rytFUPtVqSY"
    },
    {
      "tokenOwner":"",
      "amount": "779880617238902",
      "validatorVoteAccount": "juicQdAnksqZ5Yb8NQwCLjLWhykvXGktxnQCDvMe6Nx"
    },
    {
      "tokenOwner":"",
      "amount": "3322050578890122",
      "validatorVoteAccount": "AS3nKBQfKs8fJ8ncyHrdvo4FDT6S8HMRhD75JjCcyr1t"
    },
    {
      "tokenOwner":"",
      "amount": "1352494670842000",
      "validatorVoteAccount": "GNZ1PAAS33davY4Q1BMEpZEpVBtRtGvSpcTH5wYVkkVt"
    },
    {
      "tokenOwner":"",
      "amount": "1000000000000",
      "validatorVoteAccount": "4sw5oZBupkTe1g74mqCaFiw9YSrjgLbPAKtPa1Hv7LSi"
    },
    {
      "tokenOwner":"",
      "amount": "1677072859495387",
      "validatorVoteAccount": "EARNynHRWg6GfyJCmrrizcZxARB3HVzcaasvNa8kBS72"
    },
    {
      "tokenOwner":"",
      "amount": "2149285656101",
      "validatorVoteAccount": "BhbX6orFDZ9G6t3m4oSbLyW5fQNFGpjmTxgh7BraCBus"
    },
    {
      "tokenOwner":"",
      "amount": "3317635532126",
      "validatorVoteAccount": "EzbdAPRyZebKjxp7A1GGEBXY8RgimeVB8KR9mFPZqP7q"
    },
    {
      "tokenOwner":"",
      "amount": "83326907750161",
      "validatorVoteAccount": "GK9MfwWEK7BvMS8eQDaiEPnKcqMJoS7SKUiEBQY2pfxC"
    },
    {
      "tokenOwner":"",
      "amount": "8507500000000",
      "validatorVoteAccount": "Pond1QyT1sQtiru3fi9G5LGaLRGeUpJKR1a2gdbq2u4"
    },
    {
      "tokenOwner":"",
      "amount": "2294600647274660",
      "validatorVoteAccount": "CogentC52e7kktFfWHwsqSmr8LiS1yAtfqhHcftCPcBJ"
    },
    {
      "tokenOwner":"",
      "amount": "114670541483129",
      "validatorVoteAccount": "abc1zP7ihWsgQW8z5YmfQNqMckJE5Dfx8fwUNMNVNkY"
    },
    {
      "tokenOwner":"",
      "amount": "12865518106028",
      "validatorVoteAccount": "BH7asDZbKkTmT3UWiNfmMVRgQEEpXoVThGPmQfgWwDhg"
    },
    {
      "tokenOwner":"",
      "amount": "1000000000000",
      "validatorVoteAccount": "3yusuSWJXXzN8EiadtpcFZRm2FUvgaieN5d7rYifnamx"
    },
    {
      "tokenOwner":"",
      "amount": "1557290301518801",
      "validatorVoteAccount": "BWkvytz3MAiLkUbMuYK5yV1VYThbBYYQYG3gdef8NLw5"
    },
    {
      "tokenOwner":"",
      "amount": "900000000000",
      "validatorVoteAccount": "4amh4YANQfyNww8xXJYxsM7CEkFjQFJt1wpuScqy675Y"
    },
    {
      "tokenOwner":"",
      "amount": "27274870722915",
      "validatorVoteAccount": "6hZL2FZim27WkQccMfygvvXH2eow5u3wR6XUJHbMoeWP"
    },
    {
      "tokenOwner":"",
      "amount": "1253313126317",
      "validatorVoteAccount": "9cEQH7KWA74Dktk3ZQhaWi6MirzcyH8mzA3iBTxyRHsE"
    },
    {
      "tokenOwner":"",
      "amount": "3653029224586010",
      "validatorVoteAccount": "5tq4wWgnwRiJVU6nakZrBCZJ63pMEZJxmVrL2WnZ6yQv"
    },
    {
      "tokenOwner":"",
      "amount": "3262776012944716",
      "validatorVoteAccount": "Ehdn9LdjTAURQSMoDPERXLehtvzy7QD762wwPkzGT7RS"
    },
    {
      "tokenOwner":"",
      "amount": "2415602612490714",
      "validatorVoteAccount": "9xEFsHZt2mbuGQjtVGABxpeQiNeDvj54pfsJrrrUUev6"
    },
    {
      "tokenOwner":"",
      "amount": "6516267563786",
      "validatorVoteAccount": "5C9u3W5fc1Fgs9RgazrW3P5jRvyPKcoyz7CZdqkUyFYB"
    },
    {
      "tokenOwner":"",
      "amount": "1000000000000",
      "validatorVoteAccount": "MNDE6ueF5uMvyk3ohq7wWZ8H749pbpj1yHj2MvMRCJM"
    },
    {
      "tokenOwner":"",
      "amount": "1000000000000",
      "validatorVoteAccount": "5CN6gdRhBvn16f8pwhhgyuik8MYpKYv9HUdqghMe4eAw"
    },
    {
      "tokenOwner":"",
      "amount": "5171320517688",
      "validatorVoteAccount": "Gd5ngiHe5vQbDW6EbQ1wNNsvumwL1M3ranZ3xh4Wy8Hm"
    },
    {
      "tokenOwner":"",
      "amount": "44110881183491",
      "validatorVoteAccount": "ChaossQVry9AgexbXooZoWUTDfhT1x5zsAmTbBqa5142"
    },
    {
      "tokenOwner":"",
      "amount": "10999999548133",
      "validatorVoteAccount": "4nCK62aZ126pC1krepWXXxgBJGgPUGEWni2iCABZop81"
    },
    {
      "tokenOwner":"",
      "amount": "40814663488844",
      "validatorVoteAccount": "LodezVTbz3v5GK6oULfWNFfcs7D4rtMZQkmRjnh65gq"
    },
    {
      "tokenOwner":"",
      "amount": "2041335686550538",
      "validatorVoteAccount": "GREENr9zSeapgunqdMeTg8MCh2cDDn2y3py1mBGUzJYe"
    },
    {
      "tokenOwner":"",
      "amount": "79417217044746",
      "validatorVoteAccount": "3R8K6iWxNHmKSBcN3taMU2YuzfuNMRjdphnLtsG1TwZq"
    },
    {
      "tokenOwner":"",
      "amount": "28169757490035",
      "validatorVoteAccount": "DsiG71AvUHUEo9rMMHqM9NAWQ6ptguRAHyot6wGzLJjx"
    },
    {
      "tokenOwner":"",
      "amount": "4836553884195644",
      "validatorVoteAccount": "2ayMCC4aizr8RGg5ptXYqu8uoxW1whNek1hE1zaAd58z"
    },
    {
      "tokenOwner":"",
      "amount": "2000000000000",
      "validatorVoteAccount": "6JfBwvcz5QUKQJ37BMKTLrf968DDJBtwoZLw19aHwFtQ"
    },
    {
      "tokenOwner":"",
      "amount": "2848959384178801",
      "validatorVoteAccount": "5iZ5PQPy5Z9XDnkfoWPi6nvUgtxWnRFwZ36WaftPuaVM"
    },
    {
      "tokenOwner":"",
      "amount": "260119145664427",
      "validatorVoteAccount": "Va1idkzkB6LEmVFmxWbWU8Ao9qehC62Tjmf68L3uYKj"
    },
    {
      "tokenOwner":"",
      "amount": "75227499272000",
      "validatorVoteAccount": "3Xn3K5zeTzs4sURj1PCRaF6rvFg2hPgT49B4SiM998f7"
    },
    {
      "tokenOwner":"",
      "amount": "5259467387553",
      "validatorVoteAccount": "3zEbnWKibg574DaGC1EA3zLNwBK6MGQxEySUgQWKBaYV"
    },
    {
      "tokenOwner":"",
      "amount": "90999909000",
      "validatorVoteAccount": "8sZ92vJxQ3dDyf1LJiHX5A2PEmZ18cSaozHziTNRvLwF"
    },
    {
      "tokenOwner":"",
      "amount": "1000000000000",
      "validatorVoteAccount": "voteRnv6PBzmiGP8NicWtQiqEJTwKKq2SxtqtdLUJjd"
    },
    {
      "tokenOwner":"",
      "amount": "1090758292134",
      "validatorVoteAccount": "8EvEr9TchMG24F7kSE75Qdw5fcEe8qh4anVSKwj9BVfJ"
    },
    {
      "tokenOwner":"",
      "amount": "1011000000000",
      "validatorVoteAccount": "644K33yWfSzc32VvY5fRUfUqphw8LTaLQntCkyEpJ8h7"
    },
    {
      "tokenOwner":"",
      "amount": "6248591060688",
      "validatorVoteAccount": "9Gko8QZBbV5SrEvHKtQHcMrGGSfgFP3KJUozEGifu25x"
    }
  ]
}